renderwith.py
setup.py
renderwith.egg-info/PKG-INFO
renderwith.egg-info/SOURCES.txt
renderwith.egg-info/dependency_links.txt
renderwith.egg-info/top_level.txt