Metadata-Version: 1.0
Name: renderwith
Version: 0.0.1
Summary: engine-less html generation from python
Home-page: https://github.com/tengu/py-renderwith
Author: tengu
Author-email: karasuyamatengu@gmail.com
License: LGPL
Platform: UNKNOWN
Classifier: License :: OSI Approved :: GNU Library or Lesser General Public License (LGPL)
Classifier: Environment :: Console
Classifier: Programming Language :: Python
Classifier: Development Status :: 3 - Alpha
Classifier: Topic :: Utilities
